CHANGES.rst
LICENSE
MANIFEST.in
README.rst
setup.py
blocklistsaggregator.egg-info/PKG-INFO
blocklistsaggregator.egg-info/SOURCES.txt
blocklistsaggregator.egg-info/dependency_links.txt
blocklistsaggregator.egg-info/namespace_packages.txt
blocklistsaggregator.egg-info/requires.txt
blocklistsaggregator.egg-info/top_level.txt
distrib/log.ini
pierky/__init__.py
pierky/blocklistsaggregator/__init__.py
pierky/blocklistsaggregator/errors.py
pierky/blocklistsaggregator/sanitisers.py
pierky/blocklistsaggregator/version.py
pierky/blocklistsaggregator/formatters/__init__.py
pierky/blocklistsaggregator/formatters/base_formatter.py
pierky/blocklistsaggregator/formatters/cisco.py
pierky/blocklistsaggregator/formatters/json_fmt.py
pierky/blocklistsaggregator/formatters/lines.py
pierky/blocklistsaggregator/formatters/mikrotik.py
pierky/blocklistsaggregator/lists/__init__.py
pierky/blocklistsaggregator/lists/abuse_ch.py
pierky/blocklistsaggregator/lists/bambenek.py
pierky/blocklistsaggregator/lists/base_list.py
pierky/blocklistsaggregator/lists/spamhaus.py
scripts/blocklistsaggregator