Metadata-Version: 1.1
Name: blocklistsaggregator
Version: 0.5.1
Summary: A Python tool that downloads IP block lists from various sources and builds configurations for network equipments and firewalls.
Home-page: https://github.com/pierky/blocklistsaggregator
Author: Pier Carlo Chiodi
Author-email: pierky@pierky.com
License: GPLv3
Download-URL: https://github.com/pierky/blocklistsaggregator
Keywords: Malware,Spam,BlockList,Networking
Platform: UNKNOWN
Classifier: Development Status :: 4 - Beta
Classifier: Environment :: Console
Classifier: Intended Audience :: Information Technology
Classifier: Intended Audience :: System Administrators
Classifier: Intended Audience :: Telecommunications Industry
Classifier: License :: OSI Approved :: GNU General Public License v3 (GPLv3)
Classifier: Operating System :: POSIX
Classifier: Operating System :: Unix
Classifier: Programming Language :: Python
Classifier: Programming Language :: Python :: 2.7
Classifier: Programming Language :: Python :: 3.4
Classifier: Topic :: Internet :: WWW/HTTP
Classifier: Topic :: System :: Networking
Classifier: Topic :: System :: Networking :: Firewalls
Classifier: Topic :: Security
